<graph id="Graph">
  <version>1.0</version>
  <node id="Read">
    <operator>Read</operator>
    <sources/>
    <parameters class="com.bc.ceres.binding.dom.XppDomElement">
      <useAdvancedOptions>false</useAdvancedOptions>
      <file></file>
      <copyMetadata>true</copyMetadata>
      <bandNames/>
      <maskNames/>
    </parameters>
  </node>
  <node id="Apply-Orbit-File">
    <operator>Apply-Orbit-File</operator>
    <sources>
      <sourceProduct refid="Read"/>
    </sources>
    <parameters class="com.bc.ceres.binding.dom.XppDomElement">
      <orbitType>Sentinel Precise (Auto Download)</orbitType>
      <polyDegree>3</polyDegree>
      <continueOnFail>true</continueOnFail>
    </parameters>
  </node>
  <node id="Subset">
    <operator>Subset</operator>
    <sources>
      <sourceProduct refid="Apply-Orbit-File"/>
    </sources>
    <parameters class="com.bc.ceres.binding.dom.XppDomElement">
      <sourceBands/>
      <region/>
      <geoRegion></geoRegion>
      <subSamplingX>1</subSamplingX>
      <subSamplingY>1</subSamplingY>
      <fullSwath>false</fullSwath>
      <tiePointGridNames/>
      <copyMetadata>true</copyMetadata>
    </parameters>
  </node>
  <node id="ThermalNoiseRemoval">
    <operator>ThermalNoiseRemoval</operator>
    <sources>
      <sourceProduct refid="Subset"/>
    </sources>
    <parameters class="com.bc.ceres.binding.dom.XppDomElement">
      <selectedPolarisations/>
      <removeThermalNoise>true</removeThermalNoise>
      <reIntroduceThermalNoise>false</reIntroduceThermalNoise>
    </parameters>
  </node>
    <node id="Remove-GRD-Border-Noise">
    <operator>Remove-GRD-Border-Noise</operator>
    <sources>
      <sourceProduct refid="ThermalNoiseRemoval"/>
    </sources>
    <parameters class="com.bc.ceres.binding.dom.XppDomElement">
      <selectedPolarisations/>
      <borderLimit>500</borderLimit>
      <trimThreshold>50.0</trimThreshold>
    </parameters>
  </node>
  <node id="Land-Sea-Mask">
    <operator>Land-Sea-Mask</operator>
    <sources>
      <sourceProduct refid="Remove-GRD-Border-Noise"/>
    </sources>
    <parameters class="com.bc.ceres.binding.dom.XppDomElement">
      <sourceBands/>
      <landMask>false</landMask>
      <useSRTM>true</useSRTM>
      <geometry/>
      <invertGeometry>false</invertGeometry>
      <shorelineExtension>0</shorelineExtension>
    </parameters>
  </node>
  <node id="Calibration">
    <operator>Calibration</operator>
    <sources>
      <sourceProduct refid="Land-Sea-Mask"/>
    </sources>
    <parameters class="com.bc.ceres.binding.dom.XppDomElement">
      <sourceBands/>
      <auxFile>Product Auxiliary File</auxFile>
      <externalAuxFile/>
      <outputImageInComplex>false</outputImageInComplex>
      <outputImageScaleInDb>false</outputImageScaleInDb>
      <createGammaBand>false</createGammaBand>
      <createBetaBand>false</createBetaBand>
      <selectedPolarisations/>
      <outputSigmaBand>true</outputSigmaBand>
      <outputGammaBand>false</outputGammaBand>
      <outputBetaBand>false</outputBetaBand>
    </parameters>
  </node>
  <node id="Speckle-Filter">
    <operator>Speckle-Filter</operator>
    <sources>
      <sourceProduct refid="Calibration"/>
    </sources>
    <parameters class="com.bc.ceres.binding.dom.XppDomElement">
      <sourceBands/>
      <filter>Lee Sigma</filter>
      <filterSizeX>3</filterSizeX>
      <filterSizeY>3</filterSizeY>
      <dampingFactor>2</dampingFactor>
      <estimateENL>true</estimateENL>
      <enl>1.0</enl>
      <numLooksStr>1</numLooksStr>
      <windowSize>7x7</windowSize>
      <targetWindowSizeStr>3x3</targetWindowSizeStr>
      <sigmaStr>0.9</sigmaStr>
      <anSize>50</anSize>
    </parameters>
  </node>
  <node id="Terrain-Correction">
    <operator>Terrain-Correction</operator>
    <sources>
      <sourceProduct refid="Speckle-Filter"/>
    </sources>
    <parameters class="com.bc.ceres.binding.dom.XppDomElement">
      <sourceBands/>
      <demName>SRTM 1Sec HGT</demName>
      <externalDEMFile/>
      <externalDEMNoDataValue>0.0</externalDEMNoDataValue>
      <externalDEMApplyEGM>true</externalDEMApplyEGM>
      <demResamplingMethod>BILINEAR_INTERPOLATION</demResamplingMethod>
      <imgResamplingMethod>BILINEAR_INTERPOLATION</imgResamplingMethod>
      <pixelSpacingInMeter>10.0</pixelSpacingInMeter>
      <pixelSpacingInDegree>8.983152841195215E-5</pixelSpacingInDegree>
      <mapProjection>PROJCS[&quot;WGS 84 / Pseudo-Mercator&quot;, 
  GEOGCS[&quot;WGS 84&quot;, 
    DATUM[&quot;World Geodetic System 1984&quot;, 
      SPHEROID[&quot;WGS 84&quot;, 6378137.0, 298.257223563, AUTHORITY[&quot;EPSG&quot;,&quot;7030&quot;]], 
      AUTHORITY[&quot;EPSG&quot;,&quot;6326&quot;]], 
    PRIMEM[&quot;Greenwich&quot;, 0.0, AUTHORITY[&quot;EPSG&quot;,&quot;8901&quot;]], 
    UNIT[&quot;degree&quot;, 0.017453292519943295], 
    AXIS[&quot;Geodetic longitude&quot;, EAST], 
    AXIS[&quot;Geodetic latitude&quot;, NORTH], 
    AUTHORITY[&quot;EPSG&quot;,&quot;4326&quot;]], 
  PROJECTION[&quot;Popular Visualisation Pseudo Mercator&quot;], 
  PARAMETER[&quot;semi_minor&quot;, 6378137.0], 
  PARAMETER[&quot;latitude_of_origin&quot;, 0.0], 
  PARAMETER[&quot;central_meridian&quot;, 0.0], 
  PARAMETER[&quot;scale_factor&quot;, 1.0], 
  PARAMETER[&quot;false_easting&quot;, 0.0], 
  PARAMETER[&quot;false_northing&quot;, 0.0], 
  UNIT[&quot;m&quot;, 1.0], 
  AXIS[&quot;Easting&quot;, EAST], 
  AXIS[&quot;Northing&quot;, NORTH], 
  AUTHORITY[&quot;EPSG&quot;,&quot;3857&quot;]]</mapProjection>
      <alignToStandardGrid>true</alignToStandardGrid>
      <standardGridOriginX>0.0</standardGridOriginX>
      <standardGridOriginY>0.0</standardGridOriginY>
      <nodataValueAtSea>true</nodataValueAtSea>
      <saveDEM>false</saveDEM>
      <saveLatLon>false</saveLatLon>
      <saveIncidenceAngleFromEllipsoid>false</saveIncidenceAngleFromEllipsoid>
      <saveLocalIncidenceAngle>false</saveLocalIncidenceAngle>
      <saveProjectedLocalIncidenceAngle>false</saveProjectedLocalIncidenceAngle>
      <saveSelectedSourceBand>true</saveSelectedSourceBand>
      <saveLayoverShadowMask>false</saveLayoverShadowMask>
      <outputComplex>false</outputComplex>
      <applyRadiometricNormalization>false</applyRadiometricNormalization>
      <saveSigmaNought>false</saveSigmaNought>
      <saveGammaNought>false</saveGammaNought>
      <saveBetaNought>false</saveBetaNought>
      <incidenceAngleForSigma0>Use projected local incidence angle from DEM</incidenceAngleForSigma0>
      <incidenceAngleForGamma0>Use projected local incidence angle from DEM</incidenceAngleForGamma0>
      <auxFile>Latest Auxiliary File</auxFile>
      <externalAuxFile/>
    </parameters>
  </node>


  <node id="Write">
    <operator>Write</operator>
    <sources>
      <sourceProduct refid="Terrain-Correction"/>
    </sources>
    <parameters class="com.bc.ceres.binding.dom.XppDomElement">
      <file></file>
      <formatName>GeoTIFF</formatName>
    </parameters>
  </node>
</graph>